AoE2ScenarioParser/__init__.py
AoE2ScenarioParser/settings.py
AoE2ScenarioParser/version.py
AoE2ScenarioParser/datasets/__init__.py
AoE2ScenarioParser/datasets/buildings.py
AoE2ScenarioParser/datasets/conditions.py
AoE2ScenarioParser/datasets/dataset_enum.py
AoE2ScenarioParser/datasets/effects.py
AoE2ScenarioParser/datasets/heroes.py
AoE2ScenarioParser/datasets/object_support.py
AoE2ScenarioParser/datasets/other.py
AoE2ScenarioParser/datasets/players.py
AoE2ScenarioParser/datasets/projectiles.py
AoE2ScenarioParser/datasets/scenario_variant.py
AoE2ScenarioParser/datasets/techs.py
AoE2ScenarioParser/datasets/terrains.py
AoE2ScenarioParser/datasets/units.py
AoE2ScenarioParser/datasets/sources/resource_editor_names.json
AoE2ScenarioParser/datasets/sources/unit_projectile_info.json
AoE2ScenarioParser/datasets/support/__init__.py
AoE2ScenarioParser/datasets/support/info_dataset_base.py
AoE2ScenarioParser/datasets/support/dataset_gen/common.py
AoE2ScenarioParser/datasets/support/dataset_gen/gen_attr_dataset.py
AoE2ScenarioParser/datasets/support/dataset_gen/gen_res_datset.py
AoE2ScenarioParser/datasets/trigger_lists/__init__.py
AoE2ScenarioParser/datasets/trigger_lists/action_type.py
AoE2ScenarioParser/datasets/trigger_lists/age.py
AoE2ScenarioParser/datasets/trigger_lists/attack_priority.py
AoE2ScenarioParser/datasets/trigger_lists/attack_stance.py
AoE2ScenarioParser/datasets/trigger_lists/attribute.py
AoE2ScenarioParser/datasets/trigger_lists/blast_level.py
AoE2ScenarioParser/datasets/trigger_lists/blockage_class.py
AoE2ScenarioParser/datasets/trigger_lists/button_location.py
AoE2ScenarioParser/datasets/trigger_lists/charge_event.py
AoE2ScenarioParser/datasets/trigger_lists/charge_type.py
AoE2ScenarioParser/datasets/trigger_lists/color_mood.py
AoE2ScenarioParser/datasets/trigger_lists/combat_ability.py
AoE2ScenarioParser/datasets/trigger_lists/comparison.py
AoE2ScenarioParser/datasets/trigger_lists/damage_class.py
aoe2scenarioparser-0.6.5.dist-info/LICENSE
aoe2scenarioparser-0.6.5.dist-info/METADATA
aoe2scenarioparser-0.6.5.dist-info/WHEEL
aoe2scenarioparser-0.6.5.dist-info/top_level.txt
aoe2scenarioparser-0.6.5.dist-info/RECORD
