Metadata-Version: 2.1
Name: AoE2ScenarioParser
Version: 0.6.5
Summary: This is a project for editing parts of an 'aoe2scenario' file from Age of Empires 2 Definitive Edition
Author-email: Kerwin Sneijders <ksneijders-dev@hotmail.com>
Project-URL: Homepage, https://github.com/KSneijders/AoE2ScenarioParser
Project-URL: Bug Tracker, https://github.com/KSneijders/AoE2ScenarioParser/issues
Project-URL: Documentation, https://ksneijders.github.io/AoE2ScenarioParser/
Project-URL: API Docs, https://ksneijders.github.io/AoE2ScenarioParser/api_docs/aoe2_scenario/
Project-URL: Changelog, https://github.com/KSneijders/AoE2ScenarioParser/blob/master/CHANGELOG.md
Classifier: Programming Language :: Python :: 3
Classifier: License :: OSI Approved :: MIT License
Classifier: Operating System :: OS Independent
Requires-Python: >=3.8
License-File: LICENSE
Requires-Dist: deprecation
Requires-Dist: typing-extensions
Requires-Dist: ordered-set ==4.1.0
